hyprtodo/__init__.py
hyprtodo/hyprtodo.py
hyprtodo/trayLauncher.py
hyprtodo/assets/checkbox.png
hyprtodo/css/default.tcss
hyprtodo-0.1.1.dist-info/METADATA
hyprtodo-0.1.1.dist-info/WHEEL
hyprtodo-0.1.1.dist-info/entry_points.txt
hyprtodo-0.1.1.dist-info/licenses/LICENSE
hyprtodo-0.1.1.dist-info/RECORD
