Metadata-Version: 2.4
Name: hyprtodo
Version: 0.1.1
Summary: A todo list widget for Hyprland
Project-URL: Homepage, https://github.com/williamj48/hyprtodo
Project-URL: Repository, https://github.com/williamj48/hyprtodo
Author-email: William Elder <williamxelder@gmail.com>
License: MIT
License-File: LICENSE
Requires-Python: >=3.8
Requires-Dist: pyqt6
Requires-Dist: textual
